{
  "info": {
    "name": "DevFolio Backend API",
    "description": "API endpoints for testing with Postman",
    "version": "1.0.0"
  },
  "item": [
    {
      "name": "Authentication",
      "item": [
        {
          "name": "Signup",
          "request": {
            "method": "POST",
            "header": [
              {
                "key": "Content-Type",
                "value": "application/json"
              }
            ],
            "body": {
              "mode": "raw",
              "raw": "{\n  \"email\": \"test@example.com\",\n  \"password\": \"password123\"\n}"
            },
            "url": {
              "raw": "http://localhost:5000/api/users/signup",
              "protocol": "http",
              "host": ["localhost"],
              "port": "5000",
              "path": ["api", "users", "signup"]
            }
          }
        },
        {
          "name": "Login",
          "request": {
            "method": "POST",
            "header": [
              {
                "key": "Content-Type",
                "value": "application/json"
              }
            ],
            "body": {
              "mode": "raw",
              "raw": "{\n  \"email\": \"test@example.com\",\n  \"password\": \"password123\"\n}"
            },
            "url": {
              "raw": "http://localhost:5000/api/users/login",
              "protocol": "http",
              "host": ["localhost"],
              "port": "5000",
              "path": ["api", "users", "login"]
            }
          }
        }
      ]
    },
    {
      "name": "Client Onboarding Projects",
      "item": [
        {
          "name": "Create Project",
          "request": {
            "method": "POST",
            "header": [
              {
                "key": "Content-Type",
                "value": "application/json"
              },
              {
                "key": "Authorization",
                "value": "Bearer YOUR_TOKEN_HERE"
              }
            ],
            "body": {
              "mode": "raw",
              "raw": "{\n  \"clientName\": \"Aman Kumar\",\n  \"email\": \"amankumartiwari5255@gmail.com\",\n  \"phone\": \"+919031359720\",\n  \"companyName\": \"BookTech\",\n  \"projectName\": \"E-Commerce Platform\",\n  \"projectType\": \"App\",\n  \"techStack\": \"Next.js\",\n  \"startDate\": \"2025-11-01\",\n  \"deadline\": \"2025-12-08\",\n  \"totalAmount\": 8000\n}"
            },
            "url": {
              "raw": "http://localhost:5000/api/client-onboarding-projects",
              "protocol": "http",
              "host": ["localhost"],
              "port": "5000",
              "path": ["api", "client-onboarding-projects"]
            }
          }
        },
        {
          "name": "Get All Projects",
          "request": {
            "method": "GET",
            "header": [
              {
                "key": "Authorization",
                "value": "Bearer YOUR_TOKEN_HERE"
              }
            ],
            "url": {
              "raw": "http://localhost:5000/api/client-onboarding-projects",
              "protocol": "http",
              "host": ["localhost"],
              "port": "5000",
              "path": ["api", "client-onboarding-projects"]
            }
          }
        },
        {
          "name": "Get Project by ID",
          "request": {
            "method": "GET",
            "header": [
              {
                "key": "Authorization",
                "value": "Bearer YOUR_TOKEN_HERE"
              }
            ],
            "url": {
              "raw": "http://localhost:5000/api/client-onboarding-projects/PROJECT_ID",
              "protocol": "http",
              "host": ["localhost"],
              "port": "5000",
              "path": ["api", "client-onboarding-projects", "PROJECT_ID"]
            }
          }
        },
        {
          "name": "Update Project",
          "request": {
            "method": "PUT",
            "header": [
              {
                "key": "Content-Type",
                "value": "application/json"
              },
              {
                "key": "Authorization",
                "value": "Bearer YOUR_TOKEN_HERE"
              }
            ],
            "body": {
              "mode": "raw",
              "raw": "{\n  \"clientName\": \"Updated Name\",\n  \"email\": \"updated@example.com\",\n  \"phone\": \"+919876543210\",\n  \"companyName\": \"Updated Company\",\n  \"projectName\": \"Updated Project\",\n  \"projectType\": \"Website\",\n  \"techStack\": \"React\",\n  \"startDate\": \"2025-11-01\",\n  \"deadline\": \"2025-12-15\",\n  \"totalAmount\": 10000\n}"
            },
            "url": {
              "raw": "http://localhost:5000/api/client-onboarding-projects/PROJECT_ID",
              "protocol": "http",
              "host": ["localhost"],
              "port": "5000",
              "path": ["api", "client-onboarding-projects", "PROJECT_ID"]
            }
          }
        },
        {
          "name": "Update Project Stage",
          "request": {
            "method": "PATCH",
            "header": [
              {
                "key": "Content-Type",
                "value": "application/json"
              },
              {
                "key": "Authorization",
                "value": "Bearer YOUR_TOKEN_HERE"
              }
            ],
            "body": {
              "mode": "raw",
              "raw": "{\n  \"stageId\": 1,\n  \"status\": \"in-progress\",\n  \"paymentStatus\": \"partially-paid\",\n  \"notes\": \"Work in progress\",\n  \"assignedMember\": \"John Doe\"\n}"
            },
            "url": {
              "raw": "http://localhost:5000/api/client-onboarding-projects/PROJECT_ID/stage",
              "protocol": "http",
              "host": ["localhost"],
              "port": "5000",
              "path": ["api", "client-onboarding-projects", "PROJECT_ID", "stage"]
            }
          }
        },
        {
          "name": "Delete Project",
          "request": {
            "method": "DELETE",
            "header": [
              {
                "key": "Authorization",
                "value": "Bearer YOUR_TOKEN_HERE"
              }
            ],
            "url": {
              "raw": "http://localhost:5000/api/client-onboarding-projects/PROJECT_ID",
              "protocol": "http",
              "host": ["localhost"],
              "port": "5000",
              "path": ["api", "client-onboarding-projects", "PROJECT_ID"]
            }
          }
        }
      ]
    },
    {
      "name": "Health Check",
      "request": {
        "method": "GET",
        "url": {
          "raw": "http://localhost:5000/api/health",
          "protocol": "http",
          "host": ["localhost"],
          "port": "5000",
          "path": ["api", "health"]
        }
      }
    }
  ]
}
